pysyntext/__init__.py
pysyntext/anmorphacc.py
pysyntext/ccmrtrain.py
pysyntext/configdoc.md
pysyntext/predefinator.py
pysyntext/xpostrain.py
pysyntext/libs/__init__.py
pysyntext/libs/accuracy.py
pysyntext/libs/arrproc.py
pysyntext/libs/ctxmorph.py
pysyntext/libs/ctxmorphtrain.py
pysyntext/libs/cykalgo.py
pysyntext/libs/db.py
pysyntext/libs/gc.py
pysyntext/libs/logs.py
pysyntext/libs/morphology.py
pysyntext/libs/morphtrain.py
pysyntext/libs/params.py
pysyntext/libs/strproc.py
pysyntext/libs/ui.py
pysyntext/libs/tmr/__init__.py
pysyntext/libs/tmr/human.py
pysyntext/libs/tmr/trainbyaffixes.py
pysyntext/libs/ud/__init__.py
pysyntext/libs/ud/conllu.py
pysyntext/libs/ud/mte.py
pysyntext/libs/ud/mtexposdata.json
pysyntext/libs/ud/udt.py
pysyntext/libs/ud/udtxposdata.json
pysyntext-0.2.5.dist-info/LICENSE
pysyntext-0.2.5.dist-info/METADATA
pysyntext-0.2.5.dist-info/WHEEL
pysyntext-0.2.5.dist-info/top_level.txt
pysyntext-0.2.5.dist-info/RECORD
