Metadata-Version: 2.1
Name: pysyntext
Version: 0.2.5
Summary: Syntext NLP project
Home-page: https://github.com/syntpump/syntext-py-ua
Author: Syntpump
Author-email: lynnporu@gmail.com
License: MIT License
Project-URL: Syntpump on GitHub, https://github.com/syntpump
Keywords: nlp
Platform: UNKNOWN
Classifier: Development Status :: 2 - Pre-Alpha
Classifier: Intended Audience :: Developers
Classifier: Intended Audience :: Science/Research
Classifier: License :: OSI Approved :: MIT License
Requires-Python: >3
Requires-Dist: ctx19 (>=1.3)
Requires-Dist: pymongo (>=3.7.1)
